coresvc/__init__.py
coresvc/base/__init__.py
coresvc/base/base_model.py
coresvc/base/base_service.py
coresvc/comm/__init__.py
coresvc/comm/amqp_client.py
coresvc/comm/kafka_client.py
coresvc/crud/__init__.py
coresvc/crud/base_crud_sql.py
coresvc/datastore/__init__.py
coresvc/datastore/db_sql.py
coresvc/datastore/redis.py
coresvc/serializer/__init__.py
coresvc/serializer/serializer.py
coresvc/util/__init__.py
coresvc/util/random_generator.py
coresvc-0.1.9.dist-info/WHEEL
coresvc-0.1.9.dist-info/METADATA
coresvc-0.1.9.dist-info/RECORD
