Metadata-Version: 2.1
Name: coresvc
Version: 0.1.9
Summary: core services in microservice architecture
Author: MartinJ-Dev
Author-email: 29751536+MartinJ-Dev@users.noreply.github.com
Requires-Python: >=3.8,<4.0
Classifier: Programming Language :: Python :: 3
Classifier: Programming Language :: Python :: 3.8
Classifier: Programming Language :: Python :: 3.9
Requires-Dist: SQLAlchemy (>=1.3.22,<2.0.0)
Requires-Dist: aio-pika (>=6.7.1,<7.0.0)
Requires-Dist: aioredis (>=1.3.1,<2.0.0)
Requires-Dist: fastapi (>=0.63.0,<0.64.0)
Requires-Dist: faust (>=1.10.4,<2.0.0)
Requires-Dist: pydantic (>=1.7.3,<2.0.0)
Requires-Dist: requests (>=2.25.1,<3.0.0)
Requires-Dist: uvicorn[standard] (>=0.13.3,<0.14.0)
